LICENSE
MANIFEST.in
README.md
pyproject.toml
requirements.txt
setup.py
mullvad_closest/__init__.py
mullvad_closest/cli.py
mullvad_closest/utils.py
mullvad_closest.egg-info/PKG-INFO
mullvad_closest.egg-info/SOURCES.txt
mullvad_closest.egg-info/dependency_links.txt
mullvad_closest.egg-info/entry_points.txt
mullvad_closest.egg-info/requires.txt
mullvad_closest.egg-info/top_level.txt