Metadata-Version: 2.4
Name: mullvad-closest
Version: 0.0.4
Summary: Find Mullvad servers with the lowest latency at your location
Home-page: https://github.com/Ch00k/mullvad-closest
Author: Andrii Yurchuk
Author-email: ay@mntw.re
License: Unlicense
License-File: LICENSE
Requires-Dist: click
Requires-Dist: geopy
Requires-Dist: ping3
Requires-Dist: requests
Requires-Dist: tabulate
Dynamic: author
Dynamic: author-email
Dynamic: description
Dynamic: description-content-type
Dynamic: home-page
Dynamic: license
Dynamic: license-file
Dynamic: requires-dist
Dynamic: summary
